{
  "schemaVersion": 1,
  "id": "McBot",
  "version": "${version}",
  "name": "McBot",
  "description": "",
  "authors": [
    "cnlimiter"
  ],
  "contact": {
    "repo": "https://github.com/cnlimiter/Bot-Connect"
  },
  "license": "AGPL-3.0",
  "icon": "assets/McBot/icon.png",
  "environment": "server",
  "entrypoints": {
    "main": [
      "cn.evole.mods.mcbot.McBot"
    ]
  },
  "mixins": [
    "mcbot.mixins.json"
  ],
  "depends": {
    "fabricloader": "*",
    "fabric": "*",
    "minecraft": "*"
  }
}
